{
  "abilities": {

    "all": {
      "GET": [
        "/", "/users", "/logout",
        "/testimonials"
      ],
      "POST": [
        "/users/login", "/users/register"
      ]
    },

    "user": {
      "GET": [
        "/", "/users", "/logout",
        "/testimonials"
      ],
      "POST": [
        "/users/login", "/users/register"
      ]
    },

    "admin": {
      "GET": [
        "/", "/users", "/logout",
        "/testimonials"
      ],
      "PUT": [
        "/", "/users/",
        "/testimonials/"
      ],
      "POST": [
        "/users/login", "/users/register",
        "/testimonials/"
      ],
      "DELETE": [
        "/users/",
        "/testimonials/"
      ]
    },

    "superAdmin": {
      "GET": [
        "/", "/users", "/logout",
        "/testimonials"
      ],
      "PUT": [
        "/", "/users/",
        "/testimonials/"
      ],
      "POST": [
        "/users/login", "/users/register",
        "/testimonials/"
      ],
      "DELETE": [
        "/users/",
        "/testimonials/"
      ]
    }

  }
}